{
  "station_info": {
    "station_id": "MRRI-NJSEA-Meadowlands(5)",
    "station_name": "South Hackensack River",
    "latitude": 40.74179,
    "longitude": -74.07943,
    "provider": "STORET",
    "nitrate_categories": "Nitrate",
    "units_seen": "mg/L"
  },
  "summary": {
    "observation_count": 10,
    "confidence_level": "Low",
    "confidence_score": 0.5195737064824407,
    "mean_nitrate_mg_L": 4.465,
    "median_nitrate_mg_L": 3.03,
    "p90_nitrate_mg_L": 6.214999999999996,
    "max_nitrate_mg_L": 17.6,
    "min_nitrate_mg_L": 1.59,
    "first_year": 2014,
    "last_year": 2019,
    "is_hotspot": true,
    "is_p90_hotspot": true,
    "is_mean_hotspot": true
  },
  "seasonal_summary": [
    {
      "season": "Winter",
      "observation_count": 2,
      "mean_nitrate_mg_L": 3.4349999999999996,
      "median_nitrate_mg_L": 3.4349999999999996,
      "p90_nitrate_mg_L": 3.5429999999999997,
      "max_nitrate_mg_L": 3.57,
      "season_order": 1
    },
    {
      "season": "Spring",
      "observation_count": 3,
      "mean_nitrate_mg_L": 2.236666666666667,
      "median_nitrate_mg_L": 2.37,
      "p90_nitrate_mg_L": 2.49,
      "max_nitrate_mg_L": 2.52,
      "season_order": 2
    },
    {
      "season": "Summer",
      "observation_count": 3,
      "mean_nitrate_mg_L": 7.786666666666666,
      "median_nitrate_mg_L": 4.17,
      "p90_nitrate_mg_L": 14.914000000000001,
      "max_nitrate_mg_L": 17.6,
      "season_order": 3
    },
    {
      "season": "Fall",
      "observation_count": 2,
      "mean_nitrate_mg_L": 3.855,
      "median_nitrate_mg_L": 3.855,
      "p90_nitrate_mg_L": 4.731,
      "max_nitrate_mg_L": 4.95,
      "season_order": 4
    }
  ],
  "yearly_trend": [
    {
      "year": 2014.0,
      "observation_count": 1.0,
      "mean_nitrate_mg_L": 17.6,
      "median_nitrate_mg_L": 17.6,
      "p90_nitrate_mg_L": 17.6,
      "max_nitrate_mg_L": 17.6,
      "mean_3yr_moving_average": 17.6
    },
    {
      "year": 2017.0,
      "observation_count": 4.0,
      "mean_nitrate_mg_L": 3.1574999999999998,
      "median_nitrate_mg_L": 3.045,
      "p90_nitrate_mg_L": 4.5360000000000005,
      "max_nitrate_mg_L": 4.95,
      "mean_3yr_moving_average": 10.37875
    },
    {
      "year": 2018.0,
      "observation_count": 4.0,
      "mean_nitrate_mg_L": 3.15,
      "median_nitrate_mg_L": 3.03,
      "p90_nitrate_mg_L": 3.909,
      "max_nitrate_mg_L": 4.17,
      "mean_3yr_moving_average": 7.969166666666667
    },
    {
      "year": 2019.0,
      "observation_count": 1.0,
      "mean_nitrate_mg_L": 1.82,
      "median_nitrate_mg_L": 1.82,
      "p90_nitrate_mg_L": 1.82,
      "max_nitrate_mg_L": 1.82,
      "mean_3yr_moving_average": 2.7091666666666665
    }
  ],
  "monthly_trend": [
    {
      "year_month": "2014-08",
      "observation_count": 1,
      "mean_nitrate_mg_L": 17.6,
      "median_nitrate_mg_L": 17.6,
      "p90_nitrate_mg_L": 17.6,
      "max_nitrate_mg_L": 17.6,
      "date": "2014-08-01",
      "mean_6mo_moving_average": null,
      "mean_12mo_moving_average": null
    },
    {
      "year_month": "2017-02",
      "observation_count": 1,
      "mean_nitrate_mg_L": 3.57,
      "median_nitrate_mg_L": 3.57,
      "p90_nitrate_mg_L": 3.57,
      "max_nitrate_mg_L": 3.57,
      "date": "2017-02-01",
      "mean_6mo_moving_average": null,
      "mean_12mo_moving_average": null
    },
    {
      "year_month": "2017-05",
      "observation_count": 1,
      "mean_nitrate_mg_L": 2.52,
      "median_nitrate_mg_L": 2.52,
      "p90_nitrate_mg_L": 2.52,
      "max_nitrate_mg_L": 2.52,
      "date": "2017-05-01",
      "mean_6mo_moving_average": 7.896666666666667,
      "mean_12mo_moving_average": null
    },
    {
      "year_month": "2017-08",
      "observation_count": 1,
      "mean_nitrate_mg_L": 1.59,
      "median_nitrate_mg_L": 1.59,
      "p90_nitrate_mg_L": 1.59,
      "max_nitrate_mg_L": 1.59,
      "date": "2017-08-01",
      "mean_6mo_moving_average": 6.32,
      "mean_12mo_moving_average": null
    },
    {
      "year_month": "2017-11",
      "observation_count": 1,
      "mean_nitrate_mg_L": 4.95,
      "median_nitrate_mg_L": 4.95,
      "p90_nitrate_mg_L": 4.95,
      "max_nitrate_mg_L": 4.95,
      "date": "2017-11-01",
      "mean_6mo_moving_average": 6.046,
      "mean_12mo_moving_average": null
    },
    {
      "year_month": "2018-02",
      "observation_count": 1,
      "mean_nitrate_mg_L": 3.3,
      "median_nitrate_mg_L": 3.3,
      "p90_nitrate_mg_L": 3.3,
      "max_nitrate_mg_L": 3.3,
      "date": "2018-02-01",
      "mean_6mo_moving_average": 5.588333333333334,
      "mean_12mo_moving_average": 5.588333333333334
    },
    {
      "year_month": "2018-05",
      "observation_count": 1,
      "mean_nitrate_mg_L": 2.37,
      "median_nitrate_mg_L": 2.37,
      "p90_nitrate_mg_L": 2.37,
      "max_nitrate_mg_L": 2.37,
      "date": "2018-05-01",
      "mean_6mo_moving_average": 3.0500000000000003,
      "mean_12mo_moving_average": 5.128571428571428
    },
    {
      "year_month": "2018-08",
      "observation_count": 1,
      "mean_nitrate_mg_L": 4.17,
      "median_nitrate_mg_L": 4.17,
      "p90_nitrate_mg_L": 4.17,
      "max_nitrate_mg_L": 4.17,
      "date": "2018-08-01",
      "mean_6mo_moving_average": 3.15,
      "mean_12mo_moving_average": 5.00875
    },
    {
      "year_month": "2018-10",
      "observation_count": 1,
      "mean_nitrate_mg_L": 2.76,
      "median_nitrate_mg_L": 2.76,
      "p90_nitrate_mg_L": 2.76,
      "max_nitrate_mg_L": 2.76,
      "date": "2018-10-01",
      "mean_6mo_moving_average": 3.19,
      "mean_12mo_moving_average": 4.7588888888888885
    },
    {
      "year_month": "2019-05",
      "observation_count": 1,
      "mean_nitrate_mg_L": 1.82,
      "median_nitrate_mg_L": 1.82,
      "p90_nitrate_mg_L": 1.82,
      "max_nitrate_mg_L": 1.82,
      "date": "2019-05-01",
      "mean_6mo_moving_average": 3.2283333333333335,
      "mean_12mo_moving_average": 4.465
    }
  ],
  "raw_observations": [
    {
      "date": "2014-08-05",
      "year": 2014,
      "month": 8,
      "season": "Summer",
      "nitrate_mg_L": 17.6,
      "result_value": 17.6,
      "unit": "mg/L",
      "characteristic": "Nitrate",
      "nitrate_category": "Nitrate",
      "sample_fraction": "Total",
      "activity_type": "Sample-Routine",
      "provider": "STORET",
      "result_status": "Final",
      "value_type": "Actual",
      "detection_condition": null
    },
    {
      "date": "2017-02-08",
      "year": 2017,
      "month": 2,
      "season": "Winter",
      "nitrate_mg_L": 3.57,
      "result_value": 3.57,
      "unit": "mg/L",
      "characteristic": "Nitrate",
      "nitrate_category": "Nitrate",
      "sample_fraction": "Total",
      "activity_type": "Sample-Routine",
      "provider": "STORET",
      "result_status": "Final",
      "value_type": "Actual",
      "detection_condition": null
    },
    {
      "date": "2017-05-23",
      "year": 2017,
      "month": 5,
      "season": "Spring",
      "nitrate_mg_L": 2.52,
      "result_value": 2.52,
      "unit": "mg/L",
      "characteristic": "Nitrate",
      "nitrate_category": "Nitrate",
      "sample_fraction": "Total",
      "activity_type": "Sample-Routine",
      "provider": "STORET",
      "result_status": "Final",
      "value_type": "Actual",
      "detection_condition": null
    },
    {
      "date": "2017-08-01",
      "year": 2017,
      "month": 8,
      "season": "Summer",
      "nitrate_mg_L": 1.59,
      "result_value": 1.59,
      "unit": "mg/L",
      "characteristic": "Nitrate",
      "nitrate_category": "Nitrate",
      "sample_fraction": "Total",
      "activity_type": "Sample-Routine",
      "provider": "STORET",
      "result_status": "Final",
      "value_type": "Actual",
      "detection_condition": null
    },
    {
      "date": "2017-11-29",
      "year": 2017,
      "month": 11,
      "season": "Fall",
      "nitrate_mg_L": 4.95,
      "result_value": 4.95,
      "unit": "mg/L",
      "characteristic": "Nitrate",
      "nitrate_category": "Nitrate",
      "sample_fraction": "Total",
      "activity_type": "Sample-Routine",
      "provider": "STORET",
      "result_status": "Final",
      "value_type": "Actual",
      "detection_condition": null
    },
    {
      "date": "2018-02-14",
      "year": 2018,
      "month": 2,
      "season": "Winter",
      "nitrate_mg_L": 3.3,
      "result_value": 3.3,
      "unit": "mg/L",
      "characteristic": "Nitrate",
      "nitrate_category": "Nitrate",
      "sample_fraction": "Total",
      "activity_type": "Sample-Routine",
      "provider": "STORET",
      "result_status": "Final",
      "value_type": "Actual",
      "detection_condition": null
    },
    {
      "date": "2018-05-23",
      "year": 2018,
      "month": 5,
      "season": "Spring",
      "nitrate_mg_L": 2.37,
      "result_value": 2.37,
      "unit": "mg/L",
      "characteristic": "Nitrate",
      "nitrate_category": "Nitrate",
      "sample_fraction": "Total",
      "activity_type": "Sample-Routine",
      "provider": "STORET",
      "result_status": "Final",
      "value_type": "Actual",
      "detection_condition": null
    },
    {
      "date": "2018-08-07",
      "year": 2018,
      "month": 8,
      "season": "Summer",
      "nitrate_mg_L": 4.17,
      "result_value": 4.17,
      "unit": "mg/L",
      "characteristic": "Nitrate",
      "nitrate_category": "Nitrate",
      "sample_fraction": "Total",
      "activity_type": "Sample-Routine",
      "provider": "STORET",
      "result_status": "Final",
      "value_type": "Actual",
      "detection_condition": null
    },
    {
      "date": "2018-10-17",
      "year": 2018,
      "month": 10,
      "season": "Fall",
      "nitrate_mg_L": 2.76,
      "result_value": 2.76,
      "unit": "mg/L",
      "characteristic": "Nitrate",
      "nitrate_category": "Nitrate",
      "sample_fraction": "Total",
      "activity_type": "Sample-Routine",
      "provider": "STORET",
      "result_status": "Final",
      "value_type": "Actual",
      "detection_condition": null
    },
    {
      "date": "2019-05-01",
      "year": 2019,
      "month": 5,
      "season": "Spring",
      "nitrate_mg_L": 1.82,
      "result_value": 1.82,
      "unit": "mg/L",
      "characteristic": "Nitrate",
      "nitrate_category": "Nitrate",
      "sample_fraction": "Total",
      "activity_type": "Sample-Routine",
      "provider": "STORET",
      "result_status": "Final",
      "value_type": "Actual",
      "detection_condition": null
    }
  ],
  "notes": {
    "raw_observation_limit": 500,
    "confidence_rule": "High: >=100 observations; Medium: 30-99 observations; Low: <30 observations.",
    "interpretation_warning": "Low-confidence stations should not be overinterpreted."
  }
}