{
  "station_info": {
    "station_id": "NJDEP_BFBM-NJW04459-115-3",
    "station_name": "Oakford Lake - 3",
    "latitude": 40.054301,
    "longitude": -74.541386,
    "provider": "STORET",
    "nitrate_categories": "Nitrate + Nitrite",
    "units_seen": "mg/L"
  },
  "summary": {
    "observation_count": 2,
    "confidence_level": "Low",
    "confidence_score": 0.2380462838747353,
    "mean_nitrate_mg_L": 0.3075,
    "median_nitrate_mg_L": 0.3075,
    "p90_nitrate_mg_L": 0.3079,
    "max_nitrate_mg_L": 0.308,
    "min_nitrate_mg_L": 0.307,
    "first_year": 2012,
    "last_year": 2012,
    "is_hotspot": false,
    "is_p90_hotspot": false,
    "is_mean_hotspot": false
  },
  "seasonal_summary": [
    {
      "season": "Summer",
      "observation_count": 1,
      "mean_nitrate_mg_L": 0.308,
      "median_nitrate_mg_L": 0.308,
      "p90_nitrate_mg_L": 0.308,
      "max_nitrate_mg_L": 0.308,
      "season_order": 3
    },
    {
      "season": "Fall",
      "observation_count": 1,
      "mean_nitrate_mg_L": 0.307,
      "median_nitrate_mg_L": 0.307,
      "p90_nitrate_mg_L": 0.307,
      "max_nitrate_mg_L": 0.307,
      "season_order": 4
    }
  ],
  "yearly_trend": [
    {
      "year": 2012.0,
      "observation_count": 2.0,
      "mean_nitrate_mg_L": 0.3075,
      "median_nitrate_mg_L": 0.3075,
      "p90_nitrate_mg_L": 0.3079,
      "max_nitrate_mg_L": 0.308,
      "mean_3yr_moving_average": 0.3075
    }
  ],
  "monthly_trend": [
    {
      "year_month": "2012-06",
      "observation_count": 1,
      "mean_nitrate_mg_L": 0.308,
      "median_nitrate_mg_L": 0.308,
      "p90_nitrate_mg_L": 0.308,
      "max_nitrate_mg_L": 0.308,
      "date": "2012-06-01",
      "mean_6mo_moving_average": null,
      "mean_12mo_moving_average": null
    },
    {
      "year_month": "2012-10",
      "observation_count": 1,
      "mean_nitrate_mg_L": 0.307,
      "median_nitrate_mg_L": 0.307,
      "p90_nitrate_mg_L": 0.307,
      "max_nitrate_mg_L": 0.307,
      "date": "2012-10-01",
      "mean_6mo_moving_average": null,
      "mean_12mo_moving_average": null
    }
  ],
  "raw_observations": [
    {
      "date": "2012-06-12",
      "year": 2012,
      "month": 6,
      "season": "Summer",
      "nitrate_mg_L": 0.308,
      "result_value": 0.308,
      "unit": "mg/L",
      "characteristic": "Inorganic nitrogen (nitrate and nitrite) ***retired***use Nitrate + Nitrite",
      "nitrate_category": "Nitrate + Nitrite",
      "sample_fraction": "Total",
      "activity_type": "Sample-Routine",
      "provider": "STORET",
      "result_status": "Final",
      "value_type": "Actual",
      "detection_condition": null
    },
    {
      "date": "2012-10-11",
      "year": 2012,
      "month": 10,
      "season": "Fall",
      "nitrate_mg_L": 0.307,
      "result_value": 0.307,
      "unit": "mg/L",
      "characteristic": "Inorganic nitrogen (nitrate and nitrite) ***retired***use Nitrate + Nitrite",
      "nitrate_category": "Nitrate + Nitrite",
      "sample_fraction": "Total",
      "activity_type": "Sample-Routine",
      "provider": "STORET",
      "result_status": "Final",
      "value_type": "Actual",
      "detection_condition": null
    }
  ],
  "notes": {
    "raw_observation_limit": 500,
    "confidence_rule": "High: >=100 observations; Medium: 30-99 observations; Low: <30 observations.",
    "interpretation_warning": "Low-confidence stations should not be overinterpreted."
  }
}