{
  "station_info": {
    "station_id": "NJDEP_BFBM-AN0291",
    "station_name": "SADDLE R MARCELLUS PL + SADDLE R AVE",
    "latitude": 40.864083,
    "longitude": -74.101555,
    "provider": "STORET",
    "nitrate_categories": "Nitrate + Nitrite",
    "units_seen": "mg/L"
  },
  "summary": {
    "observation_count": 2,
    "confidence_level": "Low",
    "confidence_score": 0.2380462838747353,
    "mean_nitrate_mg_L": 5.15,
    "median_nitrate_mg_L": 5.15,
    "p90_nitrate_mg_L": 5.91,
    "max_nitrate_mg_L": 6.1,
    "min_nitrate_mg_L": 4.2,
    "first_year": 2018,
    "last_year": 2023,
    "is_hotspot": true,
    "is_p90_hotspot": true,
    "is_mean_hotspot": true
  },
  "seasonal_summary": [
    {
      "season": "Fall",
      "observation_count": 2,
      "mean_nitrate_mg_L": 5.15,
      "median_nitrate_mg_L": 5.15,
      "p90_nitrate_mg_L": 5.91,
      "max_nitrate_mg_L": 6.1,
      "season_order": 4
    }
  ],
  "yearly_trend": [
    {
      "year": 2018.0,
      "observation_count": 1.0,
      "mean_nitrate_mg_L": 6.1,
      "median_nitrate_mg_L": 6.1,
      "p90_nitrate_mg_L": 6.1,
      "max_nitrate_mg_L": 6.1,
      "mean_3yr_moving_average": 6.1
    },
    {
      "year": 2023.0,
      "observation_count": 1.0,
      "mean_nitrate_mg_L": 4.2,
      "median_nitrate_mg_L": 4.2,
      "p90_nitrate_mg_L": 4.2,
      "max_nitrate_mg_L": 4.2,
      "mean_3yr_moving_average": 5.15
    }
  ],
  "monthly_trend": [
    {
      "year_month": "2018-09",
      "observation_count": 1,
      "mean_nitrate_mg_L": 6.1,
      "median_nitrate_mg_L": 6.1,
      "p90_nitrate_mg_L": 6.1,
      "max_nitrate_mg_L": 6.1,
      "date": "2018-09-01",
      "mean_6mo_moving_average": null,
      "mean_12mo_moving_average": null
    },
    {
      "year_month": "2023-11",
      "observation_count": 1,
      "mean_nitrate_mg_L": 4.2,
      "median_nitrate_mg_L": 4.2,
      "p90_nitrate_mg_L": 4.2,
      "max_nitrate_mg_L": 4.2,
      "date": "2023-11-01",
      "mean_6mo_moving_average": null,
      "mean_12mo_moving_average": null
    }
  ],
  "raw_observations": [
    {
      "date": "2018-09-06",
      "year": 2018,
      "month": 9,
      "season": "Fall",
      "nitrate_mg_L": 6.1,
      "result_value": 6.1,
      "unit": "mg/L",
      "characteristic": "Nitrate + Nitrite",
      "nitrate_category": "Nitrate + Nitrite",
      "sample_fraction": "Unfiltered",
      "activity_type": "Sample-Routine",
      "provider": "STORET",
      "result_status": "Final",
      "value_type": "Actual",
      "detection_condition": null
    },
    {
      "date": "2023-11-29",
      "year": 2023,
      "month": 11,
      "season": "Fall",
      "nitrate_mg_L": 4.2,
      "result_value": 4.2,
      "unit": "mg/L",
      "characteristic": "Nitrate + Nitrite",
      "nitrate_category": "Nitrate + Nitrite",
      "sample_fraction": "Unfiltered",
      "activity_type": "Sample-Routine",
      "provider": "STORET",
      "result_status": "Final",
      "value_type": "Actual",
      "detection_condition": null
    }
  ],
  "notes": {
    "raw_observation_limit": 500,
    "confidence_rule": "High: >=100 observations; Medium: 30-99 observations; Low: <30 observations.",
    "interpretation_warning": "Low-confidence stations should not be overinterpreted."
  }
}